DFHypercode/__init__.py
DFHypercode/errors.py
DFHypercode/schemas.py
DFHypercode/typings.py
DFHypercode/utils.py
DFHypercode/classes/__init__.py
DFHypercode/classes/abc.py
DFHypercode/classes/collections.py
DFHypercode/classes/dataclass.py
DFHypercode/classes/mc_types.py
DFHypercode/classes/subcollections.py
DFHypercode/classes/variable.py
DFHypercode/codeblocks/__init__.py
DFHypercode/codeblocks/_block_utils.py
DFHypercode/codeblocks/actions.py
DFHypercode/codeblocks/caller.py
DFHypercode/codeblocks/ifs.py
DFHypercode/codeblocks/utilityblock.py
DFHypercode/codeblocks/humanized_target/__init__.py
DFHypercode/codeblocks/humanized_target/entity.py
DFHypercode/codeblocks/humanized_target/player.py
DFHypercode/constants/__init__.py
DFHypercode/constants/num_consts.py
DFHypercode/constants/regex_consts.py
DFHypercode/constants/str_consts.py
DFHypercode/constants/utility_consts.py
DFHypercode/enums/__init__.py
DFHypercode/enums/actions.py
DFHypercode/enums/callable.py
DFHypercode/enums/dftypes.py
DFHypercode/enums/enum_util.py
DFHypercode/enums/events.py
DFHypercode/enums/ifs.py
DFHypercode/enums/materials.py
DFHypercode/enums/misc_mc_enums.py
DFHypercode/enums/parameters.py
DFHypercode/enums/sounds.py
DFHypercode/enums/targets.py
DFHypercode/enums/utilityblock.py
DFHypercode/reading/__init__.py
DFHypercode/reading/callable_decorators.py
DFHypercode/reading/event_decorators.py
DFHypercode/reading/reader.py
Hypercode/__init__.py
Hypercode/errors.py
Hypercode/schemas.py
Hypercode/typings.py
Hypercode/utils.py
Hypercode/classes/__init__.py
Hypercode/classes/abc.py
Hypercode/classes/collections.py
Hypercode/classes/dataclass.py
Hypercode/classes/mc_types.py
Hypercode/classes/subcollections.py
Hypercode/classes/variable.py
Hypercode/codeblocks/__init__.py
Hypercode/codeblocks/_block_utils.py
Hypercode/codeblocks/actions.py
Hypercode/codeblocks/caller.py
Hypercode/codeblocks/ifs.py
Hypercode/codeblocks/utilityblock.py
Hypercode/codeblocks/humanized_target/__init__.py
DFHypercode-0.0.1.dist-info/LICENCE
DFHypercode-0.0.1.dist-info/METADATA
DFHypercode-0.0.1.dist-info/WHEEL
DFHypercode-0.0.1.dist-info/top_level.txt
DFHypercode-0.0.1.dist-info/RECORD
