Metadata-Version: 2.1
Name: DFHypercode
Version: 0.0.1
Summary: A tool to convert python scripts to DF code templates.
Home-page: https://github.com/TechStreetDev/Hypercode
Author: TechStreet
Author-email: author@example.com
License: MIT
Project-URL: Bug Tracker, https://github.com/TechStreetDev/Hypercode/issues
Project-URL: Source Code, https://github.com/TechStreetDev/Hypercode
Platform: UNKNOWN
Classifier: Programming Language :: Python :: 3
Classifier: License :: OSI Approved :: MIT License
Classifier: Operating System :: OS Independent
Requires-Python: >=3.6
